[
    {
        "Pub": "Faltering Fullback",
        "Area": "Finsbury Park",
        "latitude": 51.56855,
        "longitude": -0.1082097,
        "Location": 2.0,
        "Atmos": 5.0,
        "Drinks": 5.0,
        "Value": 4.0,
        "Facilities": 5.0,
        "Total": 21.0
    },
    {
        "Pub": "The Ship",
        "Area": "Wandsworth",
        "latitude": 51.46352095,
        "longitude": -0.1880008842,
        "Location": 4.0,
        "Atmos": 5.0,
        "Drinks": 3.0,
        "Value": 3.0,
        "Facilities": 5.0,
        "Total": 20.0
    },
    {
        "Pub": "Horniman At Hays",
        "Area": "London Bridge",
        "latitude": 51.5061511,
        "longitude": -0.0829614,
        "Location": 4.0,
        "Atmos": 4.0,
        "Drinks": 5.0,
        "Value": 2.0,
        "Facilities": 5.0,
        "Total": 20.0
    },
    {
        "Pub": "The Wheatsheaf",
        "Area": "Tooting",
        "latitude": 51.3716378,
        "longitude": -0.3665284,
        "Location": 3.0,
        "Atmos": 4.0,
        "Drinks": 4.0,
        "Value": 3.0,
        "Facilities": 5.0,
        "Total": 19.0
    },
    {
        "Pub": "The Devonshire",
        "Area": "Balham",
        "latitude": 51.5106275,
        "longitude": -0.1353358,
        "Location": 3.0,
        "Atmos": 4.0,
        "Drinks": 4.0,
        "Value": 3.0,
        "Facilities": 5.0,
        "Total": 19.0
    },
    {
        "Pub": "Kings Head",
        "Area": "Tooting",
        "latitude": 51.4338086428,
        "longitude": -0.16307201,
        "Location": 3.0,
        "Atmos": 4.0,
        "Drinks": 5.0,
        "Value": 3.0,
        "Facilities": 4.0,
        "Total": 19.0
    },
    {
        "Pub": "Waxy O'Connor's",
        "Area": "Leicester Square",
        "latitude": 51.510832,
        "longitude": -0.132336,
        "Location": 4.0,
        "Atmos": 4.0,
        "Drinks": 4.0,
        "Value": 3.0,
        "Facilities": 4.0,
        "Total": 19.0
    },
    {
        "Pub": "Hole in the Wall",
        "Area": "Waterloo",
        "latitude": 51.5039933403,
        "longitude": -0.1133419398,
        "Location": 3.0,
        "Atmos": 3.0,
        "Drinks": 5.0,
        "Value": 5.0,
        "Facilities": 3.0,
        "Total": 19.0
    },
    {
        "Pub": "The Devonshire",
        "Area": "Soho",
        "latitude": 51.5106275,
        "longitude": -0.1353358,
        "Location": 5.0,
        "Atmos": 5.0,
        "Drinks": 3.0,
        "Value": 3.0,
        "Facilities": 3.0,
        "Total": 19.0
    },
    {
        "Pub": "The York",
        "Area": "Angel",
        "latitude": 51.53377161,
        "longitude": -0.1049826561,
        "Location": 5.0,
        "Atmos": 4.0,
        "Drinks": 4.0,
        "Value": 3.0,
        "Facilities": 3.0,
        "Total": 19.0
    },
    {
        "Pub": "The Old Red Lion",
        "Area": "Kennington",
        "latitude": 53.4439134,
        "longitude": -1.5036302,
        "Location": 3.0,
        "Atmos": 4.0,
        "Drinks": 3.0,
        "Value": 4.0,
        "Facilities": 5.0,
        "Total": 19.0
    },
    {
        "Pub": "The King's Arms",
        "Area": "Kennington",
        "latitude": 51.48995239,
        "longitude": -0.1081661724,
        "Location": 2.0,
        "Atmos": 3.0,
        "Drinks": 4.0,
        "Value": 5.0,
        "Facilities": 5.0,
        "Total": 19.0
    },
    {
        "Pub": "Duke of Wellington",
        "Area": "Spitalfields",
        "latitude": 51.5179100256,
        "longitude": -0.0746343249,
        "Location": 3.0,
        "Atmos": 3.0,
        "Drinks": 5.0,
        "Value": 3.0,
        "Facilities": 4.0,
        "Total": 18.0
    },
    {
        "Pub": "The Falcon",
        "Area": "Clapham",
        "latitude": 51.4643102959,
        "longitude": -0.1291514718,
        "Location": 4.0,
        "Atmos": 4.0,
        "Drinks": 3.0,
        "Value": 2.0,
        "Facilities": 5.0,
        "Total": 18.0
    },
    {
        "Pub": "The Clapham Tap",
        "Area": "Clapham",
        "latitude": 51.4643196,
        "longitude": -0.135398,
        "Location": 4.0,
        "Atmos": 4.0,
        "Drinks": 2.0,
        "Value": 3.0,
        "Facilities": 5.0,
        "Total": 18.0
    },
    {
        "Pub": "The Finsbury",
        "Area": "Finsbury Park",
        "latitude": 51.571963,
        "longitude": -0.0962639,
        "Location": 3.0,
        "Atmos": 3.0,
        "Drinks": 5.0,
        "Value": 2.0,
        "Facilities": 5.0,
        "Total": 18.0
    },
    {
        "Pub": "Duke of Edinburgh",
        "Area": "Brixton",
        "latitude": 51.46328587,
        "longitude": -0.1199891453,
        "Location": 3.0,
        "Atmos": 4.0,
        "Drinks": 3.0,
        "Value": 3.0,
        "Facilities": 5.0,
        "Total": 18.0
    },
    {
        "Pub": "Fentiman Arms",
        "Area": "Oval",
        "latitude": 51.4810042,
        "longitude": -0.118221,
        "Location": 2.0,
        "Atmos": 4.0,
        "Drinks": 3.0,
        "Value": 4.0,
        "Facilities": 5.0,
        "Total": 18.0
    },
    {
        "Pub": "Constitution",
        "Area": "Camden",
        "latitude": 51.5403169435,
        "longitude": -0.1354583357,
        "Location": 3.0,
        "Atmos": 3.0,
        "Drinks": 4.0,
        "Value": 3.0,
        "Facilities": 5.0,
        "Total": 18.0
    },
    {
        "Pub": "The Albion",
        "Area": "Angel",
        "latitude": 51.539371745,
        "longitude": -0.1096085224,
        "Location": 3.0,
        "Atmos": 5.0,
        "Drinks": 3.0,
        "Value": 2.0,
        "Facilities": 5.0,
        "Total": 18.0
    },
    {
        "Pub": "The Barley Mow",
        "Area": "Marylebone",
        "latitude": 51.51970675,
        "longitude": -0.1556536263,
        "Location": 3.0,
        "Atmos": 4.0,
        "Drinks": 4.0,
        "Value": 3.0,
        "Facilities": 4.0,
        "Total": 18.0
    },
    {
        "Pub": "The Alexandra",
        "Area": "Clapham",
        "latitude": 51.461300244,
        "longitude": -0.138207107,
        "Location": 4.0,
        "Atmos": 3.0,
        "Drinks": 4.0,
        "Value": 3.0,
        "Facilities": 4.0,
        "Total": 18.0
    },
    {
        "Pub": "The Sun",
        "Area": "Clapham",
        "latitude": 51.46403152,
        "longitude": -0.1409942673,
        "Location": 4.0,
        "Atmos": 5.0,
        "Drinks": 3.0,
        "Value": 2.0,
        "Facilities": 4.0,
        "Total": 18.0
    },
    {
        "Pub": "The Avalon",
        "Area": "Balham",
        "latitude": 51.4512488692,
        "longitude": -0.1479796633,
        "Location": 3.0,
        "Atmos": 4.0,
        "Drinks": 4.0,
        "Value": 3.0,
        "Facilities": 4.0,
        "Total": 18.0
    },
    {
        "Pub": "Prince of Wales",
        "Area": "Clapham",
        "latitude": 51.46391746,
        "longitude": -0.1418578878,
        "Location": 4.0,
        "Atmos": 3.0,
        "Drinks": 3.0,
        "Value": 4.0,
        "Facilities": 4.0,
        "Total": 18.0
    },
    {
        "Pub": "The World's End",
        "Area": "Camden",
        "latitude": 51.5393406107,
        "longitude": -0.1422563677,
        "Location": 4.0,
        "Atmos": 4.0,
        "Drinks": 4.0,
        "Value": 2.0,
        "Facilities": 4.0,
        "Total": 18.0
    },
    {
        "Pub": "The Sailsbury",
        "Area": "Tottenham",
        "latitude": 51.068785,
        "longitude": -1.794472,
        "Location": 2.0,
        "Atmos": 4.0,
        "Drinks": 5.0,
        "Value": 3.0,
        "Facilities": 4.0,
        "Total": 18.0
    },
    {
        "Pub": "The Falcon",
        "Area": "Clapham Junction",
        "latitude": 51.4639442212,
        "longitude": -0.1679898101,
        "Location": 4.0,
        "Atmos": 3.0,
        "Drinks": 4.0,
        "Value": 4.0,
        "Facilities": 3.0,
        "Total": 18.0
    },
    {
        "Pub": "The Pride of Spitalfields",
        "Area": "Spitalfields",
        "latitude": 51.5189404,
        "longitude": -0.0711911,
        "Location": 3.0,
        "Atmos": 5.0,
        "Drinks": 3.0,
        "Value": 5.0,
        "Facilities": 2.0,
        "Total": 18.0
    },
    {
        "Pub": "The Chapel Market Tavern",
        "Area": "Angel",
        "latitude": 51.533426,
        "longitude": -0.111234,
        "Location": 4.0,
        "Atmos": 4.0,
        "Drinks": 4.0,
        "Value": 3.0,
        "Facilities": 3.0,
        "Total": 18.0
    },
    {
        "Pub": "The Black Prince",
        "Area": "Kennington",
        "latitude": 51.489683263,
        "longitude": -0.1121577342,
        "Location": 2.0,
        "Atmos": 4.0,
        "Drinks": 5.0,
        "Value": 2.0,
        "Facilities": 5.0,
        "Total": 18.0
    },
    {
        "Pub": "Hope & Anchor",
        "Area": "Brixton",
        "latitude": 51.46060265,
        "longitude": -0.1263557594,
        "Location": 3.0,
        "Atmos": 4.0,
        "Drinks": 2.0,
        "Value": 3.0,
        "Facilities": 5.0,
        "Total": 17.0
    },
    {
        "Pub": "Four Thieves",
        "Area": "Clapham Junction",
        "latitude": 51.4642104,
        "longitude": -0.1625657,
        "Location": 2.0,
        "Atmos": 4.0,
        "Drinks": 3.0,
        "Value": 3.0,
        "Facilities": 5.0,
        "Total": 17.0
    },
    {
        "Pub": "The Castle",
        "Area": "Tooting",
        "latitude": 51.4300228459,
        "longitude": -0.1675751106,
        "Location": 3.0,
        "Atmos": 3.0,
        "Drinks": 3.0,
        "Value": 3.0,
        "Facilities": 5.0,
        "Total": 17.0
    },
    {
        "Pub": "The George",
        "Area": "Borough",
        "latitude": 51.5045970539,
        "longitude": -0.0905283458,
        "Location": 4.0,
        "Atmos": 3.0,
        "Drinks": 3.0,
        "Value": 2.0,
        "Facilities": 5.0,
        "Total": 17.0
    },
    {
        "Pub": "The Selkirk",
        "Area": "Tooting",
        "latitude": 51.4314825379,
        "longitude": -0.1695025033,
        "Location": 2.0,
        "Atmos": 3.0,
        "Drinks": 4.0,
        "Value": 3.0,
        "Facilities": 5.0,
        "Total": 17.0
    },
    {
        "Pub": "Dutchess Belle",
        "Area": "Nine Elms",
        "latitude": 51.4791843,
        "longitude": -0.1424734,
        "Location": 3.0,
        "Atmos": 4.0,
        "Drinks": 4.0,
        "Value": 2.0,
        "Facilities": 4.0,
        "Total": 17.0
    },
    {
        "Pub": "The Landor",
        "Area": "Clapham",
        "latitude": 51.4656863,
        "longitude": -0.1260694,
        "Location": 3.0,
        "Atmos": 4.0,
        "Drinks": 4.0,
        "Value": 2.0,
        "Facilities": 4.0,
        "Total": 17.0
    },
    {
        "Pub": "Belle Vue",
        "Area": "Clapham",
        "latitude": 51.4624390656,
        "longitude": -0.1376936609,
        "Location": 4.0,
        "Atmos": 3.0,
        "Drinks": 4.0,
        "Value": 2.0,
        "Facilities": 4.0,
        "Total": 17.0
    },
    {
        "Pub": "The Stonhouse",
        "Area": "Clapham",
        "latitude": 51.4639583,
        "longitude": -0.1369942,
        "Location": 4.0,
        "Atmos": 3.0,
        "Drinks": 3.0,
        "Value": 3.0,
        "Facilities": 4.0,
        "Total": 17.0
    },
    {
        "Pub": "The Blind Beggar",
        "Area": "Whitechapel",
        "latitude": 51.5200131,
        "longitude": -0.0568989,
        "Location": 3.0,
        "Atmos": 3.0,
        "Drinks": 5.0,
        "Value": 2.0,
        "Facilities": 4.0,
        "Total": 17.0
    },
    {
        "Pub": "Tattershall Castle",
        "Area": "Whitehall",
        "latitude": 51.5044504,
        "longitude": -0.122570155,
        "Location": 5.0,
        "Atmos": 3.0,
        "Drinks": 2.0,
        "Value": 3.0,
        "Facilities": 4.0,
        "Total": 17.0
    },
    {
        "Pub": "Canton Arms",
        "Area": "Stockwell",
        "latitude": 51.4771509,
        "longitude": -0.123007,
        "Location": 3.0,
        "Atmos": 3.0,
        "Drinks": 4.0,
        "Value": 3.0,
        "Facilities": 4.0,
        "Total": 17.0
    },
    {
        "Pub": "Trinity Arms",
        "Area": "Brixton",
        "latitude": 51.4617733,
        "longitude": -0.1192909,
        "Location": 3.0,
        "Atmos": 4.0,
        "Drinks": 3.0,
        "Value": 3.0,
        "Facilities": 4.0,
        "Total": 17.0
    },
    {
        "Pub": "Phoenix",
        "Area": "Victoria",
        "latitude": 51.49868965,
        "longitude": -0.1420810506,
        "Location": 3.0,
        "Atmos": 4.0,
        "Drinks": 3.0,
        "Value": 3.0,
        "Facilities": 4.0,
        "Total": 17.0
    },
    {
        "Pub": "The Chesham Arms",
        "Area": "Hackney",
        "latitude": 51.5476074,
        "longitude": -0.0501159,
        "Location": 2.0,
        "Atmos": 5.0,
        "Drinks": 3.0,
        "Value": 3.0,
        "Facilities": 4.0,
        "Total": 17.0
    },
    {
        "Pub": "Rose & Crown",
        "Area": "Tooting",
        "latitude": 51.4340336792,
        "longitude": -0.1545338589,
        "Location": 3.0,
        "Atmos": 4.0,
        "Drinks": 3.0,
        "Value": 3.0,
        "Facilities": 4.0,
        "Total": 17.0
    },
    {
        "Pub": "Bucks Head",
        "Area": "Camden",
        "latitude": 51.2739023,
        "longitude": 0.225032,
        "Location": 4.0,
        "Atmos": 4.0,
        "Drinks": 3.0,
        "Value": 3.0,
        "Facilities": 3.0,
        "Total": 17.0
    },
    {
        "Pub": "The Twelve Pins",
        "Area": "Finsbury Park",
        "latitude": 51.56479604,
        "longitude": -0.1048136069,
        "Location": 3.0,
        "Atmos": 3.0,
        "Drinks": 5.0,
        "Value": 3.0,
        "Facilities": 3.0,
        "Total": 17.0
    },
    {
        "Pub": "The Old Star",
        "Area": "Westminster",
        "latitude": 51.5001398595,
        "longitude": -0.1336376545,
        "Location": 4.0,
        "Atmos": 3.0,
        "Drinks": 3.0,
        "Value": 4.0,
        "Facilities": 3.0,
        "Total": 17.0
    },
    {
        "Pub": "The Shacklewell Arms",
        "Area": "Dalston",
        "latitude": 51.5524017,
        "longitude": -0.071371,
        "Location": 2.0,
        "Atmos": 5.0,
        "Drinks": 4.0,
        "Value": 3.0,
        "Facilities": 3.0,
        "Total": 17.0
    },
    {
        "Pub": "The Goat",
        "Area": "Clapham Junction",
        "latitude": 51.4625099817,
        "longitude": -0.1668271239,
        "Location": 4.0,
        "Atmos": 4.0,
        "Drinks": 3.0,
        "Value": 3.0,
        "Facilities": 3.0,
        "Total": 17.0
    },
    {
        "Pub": "Bedford Arms",
        "Area": "Fulham",
        "latitude": 51.6739982,
        "longitude": -0.5284241,
        "Location": 2.0,
        "Atmos": 3.0,
        "Drinks": 5.0,
        "Value": 4.0,
        "Facilities": 3.0,
        "Total": 17.0
    },
    {
        "Pub": "Fox on the Green",
        "Area": "Angel",
        "latitude": 51.53673778,
        "longitude": -0.1031722484,
        "Location": 4.0,
        "Atmos": 3.0,
        "Drinks": 4.0,
        "Value": 3.0,
        "Facilities": 3.0,
        "Total": 17.0
    },
    {
        "Pub": "The Riverside",
        "Area": "Vauxhall",
        "latitude": 51.4863378647,
        "longitude": -0.1267290936,
        "Location": 5.0,
        "Atmos": 3.0,
        "Drinks": 3.0,
        "Value": 3.0,
        "Facilities": 3.0,
        "Total": 17.0
    },
    {
        "Pub": "The Argyll Arms",
        "Area": "Oxford Circus",
        "latitude": 51.5150755,
        "longitude": -0.141329,
        "Location": 5.0,
        "Atmos": 3.0,
        "Drinks": 3.0,
        "Value": 3.0,
        "Facilities": 3.0,
        "Total": 17.0
    },
    {
        "Pub": "Malborough Arms",
        "Area": "Fitzrovia",
        "latitude": 51.5218954,
        "longitude": -0.133703,
        "Location": 4.0,
        "Atmos": 4.0,
        "Drinks": 4.0,
        "Value": 2.0,
        "Facilities": 3.0,
        "Total": 17.0
    },
    {
        "Pub": "Montagu Pyke",
        "Area": "Soho",
        "latitude": 51.5140454,
        "longitude": -0.129887,
        "Location": 3.0,
        "Atmos": 4.0,
        "Drinks": 4.0,
        "Value": 4.0,
        "Facilities": 2.0,
        "Total": 17.0
    },
    {
        "Pub": "The Market Porter",
        "Area": "Borough",
        "latitude": 51.5053513,
        "longitude": -0.0913011,
        "Location": 4.0,
        "Atmos": 4.0,
        "Drinks": 4.0,
        "Value": 3.0,
        "Facilities": 2.0,
        "Total": 17.0
    },
    {
        "Pub": "The French House",
        "Area": "Soho",
        "latitude": 51.5127471,
        "longitude": -0.1317318,
        "Location": 5.0,
        "Atmos": 4.0,
        "Drinks": 3.0,
        "Value": 3.0,
        "Facilities": 2.0,
        "Total": 17.0
    },
    {
        "Pub": "The Alpaca",
        "Area": "Angel",
        "latitude": 51.5388014688,
        "longitude": -0.0990181998,
        "Location": 3.0,
        "Atmos": 4.0,
        "Drinks": 2.0,
        "Value": 4.0,
        "Facilities": 4.0,
        "Total": 17.0
    },
    {
        "Pub": "The Old Blue Last",
        "Area": "Shoreditch",
        "latitude": 51.5244124,
        "longitude": -0.080125,
        "Location": 3.0,
        "Atmos": 4.0,
        "Drinks": 4.0,
        "Value": 3.0,
        "Facilities": 3.0,
        "Total": 17.0
    },
    {
        "Pub": "Brewhouse",
        "Area": "Highbury",
        "latitude": 51.546511253,
        "longitude": -0.1016953176,
        "Location": 3.0,
        "Atmos": 3.0,
        "Drinks": 3.0,
        "Value": 4.0,
        "Facilities": 4.0,
        "Total": 17.0
    },
    {
        "Pub": "The Auld Shillelagh",
        "Area": "Stoke Newington",
        "latitude": 51.5620538,
        "longitude": -0.0794564,
        "Location": 2.0,
        "Atmos": 4.0,
        "Drinks": 3.0,
        "Value": 4.0,
        "Facilities": 4.0,
        "Total": 17.0
    },
    {
        "Pub": "The Southampton Arms",
        "Area": "Gospel Oak",
        "latitude": 51.5560675,
        "longitude": -0.1461834,
        "Location": 3.0,
        "Atmos": 3.0,
        "Drinks": 3.0,
        "Value": 5.0,
        "Facilities": 3.0,
        "Total": 17.0
    },
    {
        "Pub": "One Over The Ait",
        "Area": "Brentford",
        "latitude": 51.4879224,
        "longitude": -0.2883898,
        "Location": 3.0,
        "Atmos": 2.0,
        "Drinks": 4.0,
        "Value": 2.0,
        "Facilities": 5.0,
        "Total": 16.0
    },
    {
        "Pub": "Ship & Shovell",
        "Area": "Whitehall",
        "latitude": 51.5076132,
        "longitude": -0.1247324,
        "Location": 4.0,
        "Atmos": 3.0,
        "Drinks": 2.0,
        "Value": 3.0,
        "Facilities": 4.0,
        "Total": 16.0
    },
    {
        "Pub": "The Porterhouse",
        "Area": "Covent Garden",
        "latitude": 51.51206482,
        "longitude": -0.1234435191,
        "Location": 3.0,
        "Atmos": 4.0,
        "Drinks": 2.0,
        "Value": 3.0,
        "Facilities": 4.0,
        "Total": 16.0
    },
    {
        "Pub": "The Dog House",
        "Area": "Kennington",
        "latitude": 51.48937049,
        "longitude": -0.1106877877,
        "Location": 3.0,
        "Atmos": 4.0,
        "Drinks": 3.0,
        "Value": 2.0,
        "Facilities": 4.0,
        "Total": 16.0
    },
    {
        "Pub": "The Star of Kings",
        "Area": "King's Cross",
        "latitude": 51.5363747,
        "longitude": -0.1219688,
        "Location": 3.0,
        "Atmos": 4.0,
        "Drinks": 2.0,
        "Value": 3.0,
        "Facilities": 4.0,
        "Total": 16.0
    },
    {
        "Pub": "The Royal Standard",
        "Area": "Wandsworth",
        "latitude": 51.4615298461,
        "longitude": -0.1868962179,
        "Location": 3.0,
        "Atmos": 3.0,
        "Drinks": 4.0,
        "Value": 2.0,
        "Facilities": 4.0,
        "Total": 16.0
    },
    {
        "Pub": "The Angelic",
        "Area": "Angel",
        "latitude": 51.5349474385,
        "longitude": -0.1073473681,
        "Location": 4.0,
        "Atmos": 2.0,
        "Drinks": 3.0,
        "Value": 3.0,
        "Facilities": 4.0,
        "Total": 16.0
    },
    {
        "Pub": "The Scolt Head",
        "Area": "Dalston",
        "latitude": 51.5433408,
        "longitude": -0.0816201,
        "Location": 2.0,
        "Atmos": 4.0,
        "Drinks": 3.0,
        "Value": 3.0,
        "Facilities": 4.0,
        "Total": 16.0
    },
    {
        "Pub": "The King & Co",
        "Area": "Brixton",
        "latitude": 51.4594857,
        "longitude": -0.1341563,
        "Location": 2.0,
        "Atmos": 4.0,
        "Drinks": 4.0,
        "Value": 3.0,
        "Facilities": 3.0,
        "Total": 16.0
    },
    {
        "Pub": "The Admiralty",
        "Area": "Whitehall",
        "latitude": 51.5075877544,
        "longitude": -0.1288915401,
        "Location": 4.0,
        "Atmos": 4.0,
        "Drinks": 3.0,
        "Value": 2.0,
        "Facilities": 3.0,
        "Total": 16.0
    },
    {
        "Pub": "The Richmal Crompton",
        "Area": "Bromley",
        "latitude": 51.399791,
        "longitude": 0.0166824,
        "Location": 3.0,
        "Atmos": 4.0,
        "Drinks": 3.0,
        "Value": 3.0,
        "Facilities": 3.0,
        "Total": 16.0
    },
    {
        "Pub": "The Jolly Gardeners",
        "Area": "Vauxhall",
        "latitude": 51.4468727,
        "longitude": -0.189551,
        "Location": 2.0,
        "Atmos": 4.0,
        "Drinks": 3.0,
        "Value": 4.0,
        "Facilities": 3.0,
        "Total": 16.0
    },
    {
        "Pub": "Camden Head",
        "Area": "Camden",
        "latitude": 51.53730648,
        "longitude": -0.140936894,
        "Location": 3.0,
        "Atmos": 3.0,
        "Drinks": 4.0,
        "Value": 3.0,
        "Facilities": 3.0,
        "Total": 16.0
    },
    {
        "Pub": "The World's End",
        "Area": "Finsbury Park",
        "latitude": 51.5674374488,
        "longitude": -0.1082574973,
        "Location": 3.0,
        "Atmos": 3.0,
        "Drinks": 4.0,
        "Value": 3.0,
        "Facilities": 3.0,
        "Total": 16.0
    },
    {
        "Pub": "The Astronomer",
        "Area": "Liverpool Street",
        "latitude": 51.5181967056,
        "longitude": -0.0788596456,
        "Location": 3.0,
        "Atmos": 3.0,
        "Drinks": 4.0,
        "Value": 3.0,
        "Facilities": 3.0,
        "Total": 16.0
    },
    {
        "Pub": "Ye Olde Mitre",
        "Area": "Holborn",
        "latitude": 51.5184368,
        "longitude": -0.1073928,
        "Location": 3.0,
        "Atmos": 3.0,
        "Drinks": 4.0,
        "Value": 3.0,
        "Facilities": 3.0,
        "Total": 16.0
    },
    {
        "Pub": "The Perky Nel",
        "Area": "Clapham",
        "latitude": 51.4537142,
        "longitude": -0.1464228,
        "Location": 3.0,
        "Atmos": 3.0,
        "Drinks": 4.0,
        "Value": 3.0,
        "Facilities": 3.0,
        "Total": 16.0
    },
    {
        "Pub": "The Grafton Arms",
        "Area": "Fitzrovia",
        "latitude": 51.5232472,
        "longitude": -0.1386611,
        "Location": 3.0,
        "Atmos": 3.0,
        "Drinks": 3.0,
        "Value": 4.0,
        "Facilities": 3.0,
        "Total": 16.0
    },
    {
        "Pub": "The George & Vulture",
        "Area": "Shoreditch",
        "latitude": 51.5291724,
        "longitude": -0.0837297,
        "Location": 2.0,
        "Atmos": 3.0,
        "Drinks": 5.0,
        "Value": 3.0,
        "Facilities": 3.0,
        "Total": 16.0
    },
    {
        "Pub": "The Marquis of Granbry",
        "Area": "Westminster",
        "latitude": 51.495358718,
        "longitude": -0.1270892299,
        "Location": 3.0,
        "Atmos": 3.0,
        "Drinks": 4.0,
        "Value": 3.0,
        "Facilities": 3.0,
        "Total": 16.0
    },
    {
        "Pub": "Ninth Life",
        "Area": "Catford",
        "latitude": 51.4475538065,
        "longitude": -0.0187251911,
        "Location": 3.0,
        "Atmos": 3.0,
        "Drinks": 3.0,
        "Value": 4.0,
        "Facilities": 3.0,
        "Total": 16.0
    },
    {
        "Pub": "The Hen & Chickens",
        "Area": "Highbury",
        "latitude": 51.54604063,
        "longitude": -0.1019998298,
        "Location": 4.0,
        "Atmos": 3.0,
        "Drinks": 3.0,
        "Value": 3.0,
        "Facilities": 3.0,
        "Total": 16.0
    },
    {
        "Pub": "The Exmouth Arms",
        "Area": "Clerkenwell",
        "latitude": 51.52574913,
        "longitude": -0.109674361,
        "Location": 3.0,
        "Atmos": 5.0,
        "Drinks": 2.0,
        "Value": 3.0,
        "Facilities": 3.0,
        "Total": 16.0
    },
    {
        "Pub": "The Railway",
        "Area": "Clapham",
        "latitude": 51.4647673655,
        "longitude": -0.1312365122,
        "Location": 4.0,
        "Atmos": 3.0,
        "Drinks": 4.0,
        "Value": 3.0,
        "Facilities": 2.0,
        "Total": 16.0
    },
    {
        "Pub": "The Observatory",
        "Area": "Greenwich",
        "latitude": 51.50435904,
        "longitude": 0.0036083152,
        "Location": 4.0,
        "Atmos": 3.0,
        "Drinks": 4.0,
        "Value": 3.0,
        "Facilities": 2.0,
        "Total": 16.0
    },
    {
        "Pub": "Walkers of Whitehall",
        "Area": "Whitehall",
        "latitude": 51.5067778,
        "longitude": -0.126887,
        "Location": 4.0,
        "Atmos": 4.0,
        "Drinks": 4.0,
        "Value": 2.0,
        "Facilities": 2.0,
        "Total": 16.0
    },
    {
        "Pub": "Mayfair Tavern",
        "Area": "Tooting",
        "latitude": 51.43236767,
        "longitude": -0.1636610784,
        "Location": 3.0,
        "Atmos": 4.0,
        "Drinks": 4.0,
        "Value": 3.0,
        "Facilities": 2.0,
        "Total": 16.0
    },
    {
        "Pub": "The Coach & Horses",
        "Area": "Soho",
        "latitude": 51.5132483,
        "longitude": -0.1301679,
        "Location": 5.0,
        "Atmos": 4.0,
        "Drinks": 3.0,
        "Value": 2.0,
        "Facilities": 2.0,
        "Total": 16.0
    },
    {
        "Pub": "The Prince of Wales",
        "Area": "Kennington",
        "latitude": 51.48820678,
        "longitude": -0.1090793261,
        "Location": 3.0,
        "Atmos": 4.0,
        "Drinks": 3.0,
        "Value": 3.0,
        "Facilities": 3.0,
        "Total": 16.0
    },
    {
        "Pub": "The Three Johns",
        "Area": "Angel",
        "latitude": 51.5329792745,
        "longitude": -0.1090703966,
        "Location": 4.0,
        "Atmos": 4.0,
        "Drinks": 2.0,
        "Value": 2.0,
        "Facilities": 3.0,
        "Total": 15.0
    },
    {
        "Pub": "The Prince",
        "Area": "Fulham",
        "latitude": 51.4884539093,
        "longitude": -0.1968627023,
        "Location": 3.0,
        "Atmos": 4.0,
        "Drinks": 2.0,
        "Value": 2.0,
        "Facilities": 4.0,
        "Total": 15.0
    },
    {
        "Pub": "The Tim Bobbin",
        "Area": "Clapham",
        "latitude": 51.46633831,
        "longitude": -0.1428777373,
        "Location": 3.0,
        "Atmos": 3.0,
        "Drinks": 3.0,
        "Value": 2.0,
        "Facilities": 4.0,
        "Total": 15.0
    },
    {
        "Pub": "The Windmill",
        "Area": "Clapham",
        "latitude": 51.4579278,
        "longitude": -0.144160218,
        "Location": 4.0,
        "Atmos": 2.0,
        "Drinks": 3.0,
        "Value": 2.0,
        "Facilities": 4.0,
        "Total": 15.0
    },
    {
        "Pub": "The Saxon",
        "Area": "Clapham",
        "latitude": 51.4642214847,
        "longitude": -0.1327569119,
        "Location": 4.0,
        "Atmos": 2.0,
        "Drinks": 3.0,
        "Value": 2.0,
        "Facilities": 4.0,
        "Total": 15.0
    },
    {
        "Pub": "Bread & Roses",
        "Area": "Clapham",
        "latitude": 51.4662721354,
        "longitude": -0.1363359915,
        "Location": 3.0,
        "Atmos": 2.0,
        "Drinks": 4.0,
        "Value": 2.0,
        "Facilities": 4.0,
        "Total": 15.0
    },
    {
        "Pub": "Catford Bridge Tavern",
        "Area": "Catford",
        "latitude": 51.444615,
        "longitude": -0.0245057,
        "Location": 3.0,
        "Atmos": 2.0,
        "Drinks": 3.0,
        "Value": 3.0,
        "Facilities": 4.0,
        "Total": 15.0
    },
    {
        "Pub": "The Coach Makers Arms",
        "Area": "Marylebone",
        "latitude": 51.5171805,
        "longitude": -0.1506242,
        "Location": 3.0,
        "Atmos": 4.0,
        "Drinks": 2.0,
        "Value": 2.0,
        "Facilities": 4.0,
        "Total": 15.0
    },
    {
        "Pub": "The George & Monkey",
        "Area": "Angel",
        "latitude": 51.5299178,
        "longitude": -0.1102592,
        "Location": 3.0,
        "Atmos": 2.0,
        "Drinks": 3.0,
        "Value": 3.0,
        "Facilities": 4.0,
        "Total": 15.0
    },
    {
        "Pub": "Barley Mow",
        "Area": "Westminster",
        "latitude": 51.49500556,
        "longitude": -0.1317804613,
        "Location": 3.0,
        "Atmos": 4.0,
        "Drinks": 3.0,
        "Value": 2.0,
        "Facilities": 3.0,
        "Total": 15.0
    },
    {
        "Pub": "The Albert",
        "Area": "Westminster",
        "latitude": 51.4978414872,
        "longitude": -0.1355005388,
        "Location": 3.0,
        "Atmos": 3.0,
        "Drinks": 4.0,
        "Value": 2.0,
        "Facilities": 3.0,
        "Total": 15.0
    },
    {
        "Pub": "Nolan's",
        "Area": "Nine Elms",
        "latitude": 51.4798190525,
        "longitude": -0.1260624836,
        "Location": 2.0,
        "Atmos": 3.0,
        "Drinks": 3.0,
        "Value": 4.0,
        "Facilities": 3.0,
        "Total": 15.0
    },
    {
        "Pub": "Waterloo Tap",
        "Area": "Waterloo",
        "latitude": 51.5045521,
        "longitude": -0.1150203,
        "Location": 4.0,
        "Atmos": 2.0,
        "Drinks": 3.0,
        "Value": 3.0,
        "Facilities": 3.0,
        "Total": 15.0
    },
    {
        "Pub": "Bucks Head",
        "Area": "Camden",
        "latitude": 51.2739023,
        "longitude": 0.225032,
        "Location": 4.0,
        "Atmos": 3.0,
        "Drinks": 2.0,
        "Value": 3.0,
        "Facilities": 3.0,
        "Total": 15.0
    },
    {
        "Pub": "The Camel and Artichoke",
        "Area": "Waterloo",
        "latitude": 51.5007422,
        "longitude": -0.1132459,
        "Location": 3.0,
        "Atmos": 2.0,
        "Drinks": 4.0,
        "Value": 3.0,
        "Facilities": 3.0,
        "Total": 15.0
    },
    {
        "Pub": "Colonies",
        "Area": "Westminster",
        "latitude": 51.4989426325,
        "longitude": -0.1396704507,
        "Location": 3.0,
        "Atmos": 4.0,
        "Drinks": 3.0,
        "Value": 2.0,
        "Facilities": 3.0,
        "Total": 15.0
    },
    {
        "Pub": "The Duke of Sussex",
        "Area": "Waterloo",
        "latitude": 51.5020786711,
        "longitude": -0.1097357594,
        "Location": 4.0,
        "Atmos": 3.0,
        "Drinks": 3.0,
        "Value": 2.0,
        "Facilities": 3.0,
        "Total": 15.0
    },
    {
        "Pub": "Crate Brewery",
        "Area": "Hackney Wick",
        "latitude": 51.5429659,
        "longitude": -0.0221165,
        "Location": 3.0,
        "Atmos": 3.0,
        "Drinks": 3.0,
        "Value": 3.0,
        "Facilities": 3.0,
        "Total": 15.0
    },
    {
        "Pub": "The Cow",
        "Area": "Stratford",
        "latitude": 51.5454838826,
        "longitude": 0.008214455,
        "Location": 4.0,
        "Atmos": 2.0,
        "Drinks": 4.0,
        "Value": 2.0,
        "Facilities": 3.0,
        "Total": 15.0
    },
    {
        "Pub": "The Gregorian",
        "Area": "Bermondsey",
        "latitude": 51.4979551992,
        "longitude": -0.0664905459,
        "Location": 3.0,
        "Atmos": 3.0,
        "Drinks": 3.0,
        "Value": 3.0,
        "Facilities": 3.0,
        "Total": 15.0
    },
    {
        "Pub": "The Clerkenwell Tavern",
        "Area": "Clerkenwell",
        "latitude": 51.5250475,
        "longitude": -0.1103013,
        "Location": 3.0,
        "Atmos": 4.0,
        "Drinks": 2.0,
        "Value": 3.0,
        "Facilities": 3.0,
        "Total": 15.0
    },
    {
        "Pub": "Brewmaster",
        "Area": "Leicester Square",
        "latitude": 51.5114757,
        "longitude": -0.1281224461,
        "Location": 4.0,
        "Atmos": 3.0,
        "Drinks": 3.0,
        "Value": 3.0,
        "Facilities": 2.0,
        "Total": 15.0
    },
    {
        "Pub": "White Hart",
        "Area": "Covent Garden",
        "latitude": 51.4137452888,
        "longitude": -0.3002781456,
        "Location": 3.0,
        "Atmos": 3.0,
        "Drinks": 5.0,
        "Value": 2.0,
        "Facilities": 2.0,
        "Total": 15.0
    },
    {
        "Pub": "The Kings Tun",
        "Area": "Kingston",
        "latitude": 51.411487,
        "longitude": -0.3005416,
        "Location": 3.0,
        "Atmos": 2.0,
        "Drinks": 4.0,
        "Value": 4.0,
        "Facilities": 2.0,
        "Total": 15.0
    },
    {
        "Pub": "The Feathers",
        "Area": "Westminster",
        "latitude": 51.4994224726,
        "longitude": -0.1330910367,
        "Location": 4.0,
        "Atmos": 3.0,
        "Drinks": 3.0,
        "Value": 3.0,
        "Facilities": 2.0,
        "Total": 15.0
    },
    {
        "Pub": "The Railway Tavern",
        "Area": "Dalston",
        "latitude": 51.54876416,
        "longitude": -0.0793085774,
        "Location": 2.0,
        "Atmos": 4.0,
        "Drinks": 4.0,
        "Value": 3.0,
        "Facilities": 2.0,
        "Total": 15.0
    },
    {
        "Pub": "The Speaker",
        "Area": "Westminster",
        "latitude": 51.4970081092,
        "longitude": -0.1323035693,
        "Location": 3.0,
        "Atmos": 4.0,
        "Drinks": 4.0,
        "Value": 2.0,
        "Facilities": 2.0,
        "Total": 15.0
    },
    {
        "Pub": "The King's Head",
        "Area": "Mayfair",
        "latitude": 51.5086516,
        "longitude": -0.1412775231,
        "Location": 4.0,
        "Atmos": 3.0,
        "Drinks": 2.0,
        "Value": 4.0,
        "Facilities": 2.0,
        "Total": 15.0
    },
    {
        "Pub": "The Beehive",
        "Area": "Brixton",
        "latitude": 51.4642491183,
        "longitude": -0.1141790333,
        "Location": 3.0,
        "Atmos": 2.0,
        "Drinks": 4.0,
        "Value": 5.0,
        "Facilities": 1.0,
        "Total": 15.0
    },
    {
        "Pub": "The Alwyne Castle",
        "Area": "Highbury",
        "latitude": 51.5465734,
        "longitude": -0.0985023,
        "Location": 3.0,
        "Atmos": 3.0,
        "Drinks": 3.0,
        "Value": 2.0,
        "Facilities": 4.0,
        "Total": 15.0
    },
    {
        "Pub": "The Ten Bells",
        "Area": "Spitalfields",
        "latitude": 51.51936435,
        "longitude": -0.0742931862,
        "Location": 3.0,
        "Atmos": 4.0,
        "Drinks": 3.0,
        "Value": 2.0,
        "Facilities": 3.0,
        "Total": 15.0
    },
    {
        "Pub": "Vineyard",
        "Area": "Islington",
        "latitude": 51.5423759124,
        "longitude": -0.1036217597,
        "Location": 3.0,
        "Atmos": 2.0,
        "Drinks": 4.0,
        "Value": 2.0,
        "Facilities": 4.0,
        "Total": 15.0
    },
    {
        "Pub": "The Old Bull and Bush",
        "Area": "Hampstead",
        "latitude": 51.5686746572,
        "longitude": -0.1815958845,
        "Location": 2.0,
        "Atmos": 3.0,
        "Drinks": 3.0,
        "Value": 3.0,
        "Facilities": 4.0,
        "Total": 15.0
    },
    {
        "Pub": "Bank of Friendship",
        "Area": "Highbury",
        "latitude": 51.558357,
        "longitude": -0.0986983,
        "Location": 2.0,
        "Atmos": 3.0,
        "Drinks": 2.0,
        "Value": 3.0,
        "Facilities": 4.0,
        "Total": 14.0
    },
    {
        "Pub": "Priory Arms",
        "Area": "Stockwell",
        "latitude": 51.4748511,
        "longitude": -0.12834,
        "Location": 2.0,
        "Atmos": 3.0,
        "Drinks": 3.0,
        "Value": 3.0,
        "Facilities": 3.0,
        "Total": 14.0
    },
    {
        "Pub": "The Thirsty Bear",
        "Area": "Waterloo",
        "latitude": 51.5071142,
        "longitude": -0.1081282,
        "Location": 3.0,
        "Atmos": 3.0,
        "Drinks": 3.0,
        "Value": 2.0,
        "Facilities": 3.0,
        "Total": 14.0
    },
    {
        "Pub": "The Mason's Arms",
        "Area": "Battersea",
        "latitude": 51.47682323,
        "longitude": -0.1468925149,
        "Location": 3.0,
        "Atmos": 3.0,
        "Drinks": 3.0,
        "Value": 2.0,
        "Facilities": 3.0,
        "Total": 14.0
    },
    {
        "Pub": "Porter and Sorter",
        "Area": "Croydon",
        "latitude": 51.3759845,
        "longitude": -0.0918666,
        "Location": 3.0,
        "Atmos": 2.0,
        "Drinks": 4.0,
        "Value": 2.0,
        "Facilities": 3.0,
        "Total": 14.0
    },
    {
        "Pub": "The Barrel Vault",
        "Area": "King's Cross",
        "latitude": 51.5325134,
        "longitude": -0.1262881,
        "Location": 4.0,
        "Atmos": 2.0,
        "Drinks": 3.0,
        "Value": 2.0,
        "Facilities": 3.0,
        "Total": 14.0
    },
    {
        "Pub": "The Crown",
        "Area": "Angel",
        "latitude": 51.5375589834,
        "longitude": -0.1094874638,
        "Location": 3.0,
        "Atmos": 3.0,
        "Drinks": 2.0,
        "Value": 3.0,
        "Facilities": 3.0,
        "Total": 14.0
    },
    {
        "Pub": "The Regent",
        "Area": "Angel",
        "latitude": 51.5390895386,
        "longitude": -0.1069837899,
        "Location": 3.0,
        "Atmos": 2.0,
        "Drinks": 2.0,
        "Value": 4.0,
        "Facilities": 3.0,
        "Total": 14.0
    },
    {
        "Pub": "The Beer House",
        "Area": "Victoria",
        "latitude": 51.49552609,
        "longitude": -0.1432911184,
        "Location": 4.0,
        "Atmos": 2.0,
        "Drinks": 3.0,
        "Value": 2.0,
        "Facilities": 3.0,
        "Total": 14.0
    },
    {
        "Pub": "The Fitzrovia Bell",
        "Area": "Fitzrovia",
        "latitude": 51.5225338,
        "longitude": -0.1358954,
        "Location": 3.0,
        "Atmos": 2.0,
        "Drinks": 3.0,
        "Value": 3.0,
        "Facilities": 3.0,
        "Total": 14.0
    },
    {
        "Pub": "Two Chairmen",
        "Area": "Westminster",
        "latitude": 51.5006512,
        "longitude": -0.1316457,
        "Location": 3.0,
        "Atmos": 3.0,
        "Drinks": 3.0,
        "Value": 3.0,
        "Facilities": 2.0,
        "Total": 14.0
    },
    {
        "Pub": "Silver Cross",
        "Area": "Whitehall",
        "latitude": 51.5066724112,
        "longitude": -0.1270202201,
        "Location": 4.0,
        "Atmos": 2.0,
        "Drinks": 3.0,
        "Value": 3.0,
        "Facilities": 2.0,
        "Total": 14.0
    },
    {
        "Pub": "Old Town Tavern",
        "Area": "Clapham",
        "latitude": 51.46612141,
        "longitude": -0.1421673202,
        "Location": 3.0,
        "Atmos": 3.0,
        "Drinks": 4.0,
        "Value": 2.0,
        "Facilities": 2.0,
        "Total": 14.0
    },
    {
        "Pub": "Grafton Arms",
        "Area": "Westminster",
        "latitude": 51.49747612,
        "longitude": -0.1340325474,
        "Location": 3.0,
        "Atmos": 3.0,
        "Drinks": 4.0,
        "Value": 2.0,
        "Facilities": 2.0,
        "Total": 14.0
    },
    {
        "Pub": "Adam and Eve",
        "Area": "Westminster",
        "latitude": 51.499602339,
        "longitude": -0.135695391,
        "Location": 3.0,
        "Atmos": 3.0,
        "Drinks": 4.0,
        "Value": 2.0,
        "Facilities": 2.0,
        "Total": 14.0
    },
    {
        "Pub": "The Royal Oak",
        "Area": "Westminster",
        "latitude": 51.4943026461,
        "longitude": -0.1325210127,
        "Location": 3.0,
        "Atmos": 3.0,
        "Drinks": 3.0,
        "Value": 3.0,
        "Facilities": 2.0,
        "Total": 14.0
    },
    {
        "Pub": "Bayswater Arms",
        "Area": "Bayswater",
        "latitude": 51.5127199,
        "longitude": -0.1877793,
        "Location": 3.0,
        "Atmos": 3.0,
        "Drinks": 4.0,
        "Value": 2.0,
        "Facilities": 2.0,
        "Total": 14.0
    },
    {
        "Pub": "The Greencoat Boy",
        "Area": "Westminster",
        "latitude": 51.4963188,
        "longitude": -0.1358602,
        "Location": 3.0,
        "Atmos": 3.0,
        "Drinks": 3.0,
        "Value": 3.0,
        "Facilities": 2.0,
        "Total": 14.0
    },
    {
        "Pub": "The Fellow",
        "Area": "King's Cross",
        "latitude": 51.5321420417,
        "longitude": -0.1220365495,
        "Location": 4.0,
        "Atmos": 3.0,
        "Drinks": 3.0,
        "Value": 2.0,
        "Facilities": 2.0,
        "Total": 14.0
    },
    {
        "Pub": "The Roundhouse",
        "Area": "Covent Garden",
        "latitude": 51.51126538,
        "longitude": -0.1255310526,
        "Location": 3.0,
        "Atmos": 3.0,
        "Drinks": 3.0,
        "Value": 3.0,
        "Facilities": 2.0,
        "Total": 14.0
    },
    {
        "Pub": "Fire Station",
        "Area": "Waterloo",
        "latitude": 51.5024600379,
        "longitude": -0.1104892081,
        "Location": 4.0,
        "Atmos": 3.0,
        "Drinks": 3.0,
        "Value": 2.0,
        "Facilities": 2.0,
        "Total": 14.0
    },
    {
        "Pub": "The Phoenix",
        "Area": "Stockwell",
        "latitude": 51.4695415579,
        "longitude": -0.1273172284,
        "Location": 2.0,
        "Atmos": 2.0,
        "Drinks": 4.0,
        "Value": 4.0,
        "Facilities": 2.0,
        "Total": 14.0
    },
    {
        "Pub": "Shakespeare",
        "Area": "Victoria",
        "latitude": 51.4964182439,
        "longitude": -0.1448258055,
        "Location": 4.0,
        "Atmos": 2.0,
        "Drinks": 4.0,
        "Value": 2.0,
        "Facilities": 2.0,
        "Total": 14.0
    },
    {
        "Pub": "The Sanctuary",
        "Area": "Westminster",
        "latitude": 51.5000706224,
        "longitude": -0.1316359297,
        "Location": 4.0,
        "Atmos": 3.0,
        "Drinks": 3.0,
        "Value": 2.0,
        "Facilities": 2.0,
        "Total": 14.0
    },
    {
        "Pub": "The Northumberland Arms",
        "Area": "Fitzrovia",
        "latitude": 51.52353994,
        "longitude": -0.1374015359,
        "Location": 4.0,
        "Atmos": 2.0,
        "Drinks": 2.0,
        "Value": 4.0,
        "Facilities": 2.0,
        "Total": 14.0
    },
    {
        "Pub": "Coach and Horses",
        "Area": "Soho",
        "latitude": 51.5139723969,
        "longitude": -0.1296443433,
        "Location": 3.0,
        "Atmos": 4.0,
        "Drinks": 4.0,
        "Value": 2.0,
        "Facilities": 1.0,
        "Total": 14.0
    },
    {
        "Pub": "The Griffin",
        "Area": "Shoreditch",
        "latitude": 51.5249680871,
        "longitude": -0.081983411,
        "Location": 3.0,
        "Atmos": 4.0,
        "Drinks": 2.0,
        "Value": 3.0,
        "Facilities": 2.0,
        "Total": 14.0
    },
    {
        "Pub": "The Culpeper",
        "Area": "Spitalfields",
        "latitude": 51.51692806,
        "longitude": -0.0730303947,
        "Location": 3.0,
        "Atmos": 3.0,
        "Drinks": 2.0,
        "Value": 2.0,
        "Facilities": 4.0,
        "Total": 14.0
    },
    {
        "Pub": "The Morpeth Arms",
        "Area": "Westminster",
        "latitude": 51.4894082,
        "longitude": -0.1287178,
        "Location": 3.0,
        "Atmos": 3.0,
        "Drinks": 2.0,
        "Value": 2.0,
        "Facilities": 3.0,
        "Total": 13.0
    },
    {
        "Pub": "The Grosvenor Arms",
        "Area": "Brixton",
        "latitude": 51.46992439,
        "longitude": -0.1172734415,
        "Location": 2.0,
        "Atmos": 4.0,
        "Drinks": 3.0,
        "Value": 2.0,
        "Facilities": 2.0,
        "Total": 13.0
    },
    {
        "Pub": "Duke of York",
        "Area": "Victoria",
        "latitude": 51.4968548998,
        "longitude": -0.1428349925,
        "Location": 3.0,
        "Atmos": 3.0,
        "Drinks": 2.0,
        "Value": 3.0,
        "Facilities": 2.0,
        "Total": 13.0
    },
    {
        "Pub": "The Kings Head",
        "Area": "Bayswater",
        "latitude": 51.5092902445,
        "longitude": -0.1414277059,
        "Location": 3.0,
        "Atmos": 2.0,
        "Drinks": 3.0,
        "Value": 3.0,
        "Facilities": 2.0,
        "Total": 13.0
    },
    {
        "Pub": "The Hanover Arms",
        "Area": "Oval",
        "latitude": 51.4814475,
        "longitude": -0.1131384,
        "Location": 4.0,
        "Atmos": 2.0,
        "Drinks": 4.0,
        "Value": 1.0,
        "Facilities": 2.0,
        "Total": 13.0
    },
    {
        "Pub": "The Camden Eye",
        "Area": "Camden",
        "latitude": 51.5394953,
        "longitude": -0.1422158,
        "Location": 4.0,
        "Atmos": 4.0,
        "Drinks": 2.0,
        "Value": 2.0,
        "Facilities": 1.0,
        "Total": 13.0
    },
    {
        "Pub": "The Tommyfield",
        "Area": "Kennington",
        "latitude": 51.4886535,
        "longitude": -0.1108664,
        "Location": 3.0,
        "Atmos": 2.0,
        "Drinks": 3.0,
        "Value": 3.0,
        "Facilities": 2.0,
        "Total": 13.0
    },
    {
        "Pub": "Rose & Crown",
        "Area": "Southwark",
        "latitude": 51.5058273129,
        "longitude": -0.1058852331,
        "Location": 2.0,
        "Atmos": 2.0,
        "Drinks": 2.0,
        "Value": 3.0,
        "Facilities": 3.0,
        "Total": 12.0
    },
    {
        "Pub": "The Red Lion",
        "Area": "Whitehall",
        "latitude": 51.5025306146,
        "longitude": -0.1258473145,
        "Location": 4.0,
        "Atmos": 3.0,
        "Drinks": 1.0,
        "Value": 2.0,
        "Facilities": 2.0,
        "Total": 12.0
    },
    {
        "Pub": "Prince Alfred",
        "Area": "Bayswater",
        "latitude": 51.5137487425,
        "longitude": -0.1876295566,
        "Location": 3.0,
        "Atmos": 2.0,
        "Drinks": 3.0,
        "Value": 2.0,
        "Facilities": 2.0,
        "Total": 12.0
    },
    {
        "Pub": "Rose & Crown",
        "Area": "Clapham",
        "latitude": 51.4637145708,
        "longitude": -0.1413194496,
        "Location": 4.0,
        "Atmos": 1.0,
        "Drinks": 3.0,
        "Value": 2.0,
        "Facilities": 2.0,
        "Total": 12.0
    },
    {
        "Pub": "Clapham North",
        "Area": "Clapham",
        "latitude": 51.4653972,
        "longitude": -0.1290355,
        "Location": 4.0,
        "Atmos": 1.0,
        "Drinks": 3.0,
        "Value": 2.0,
        "Facilities": 2.0,
        "Total": 12.0
    },
    {
        "Pub": "Crown & Sceptre",
        "Area": "Kensington",
        "latitude": 51.4979640146,
        "longitude": -0.2074636666,
        "Location": 4.0,
        "Atmos": 1.0,
        "Drinks": 4.0,
        "Value": 1.0,
        "Facilities": 2.0,
        "Total": 12.0
    },
    {
        "Pub": "All My Friends",
        "Area": "Hackney Wick",
        "latitude": 51.5425861917,
        "longitude": -0.0218480284,
        "Location": 3.0,
        "Atmos": 2.0,
        "Drinks": 2.0,
        "Value": 3.0,
        "Facilities": 2.0,
        "Total": 12.0
    },
    {
        "Pub": "The Islington Town House",
        "Area": "Angel",
        "latitude": 51.5337287,
        "longitude": -0.1071819,
        "Location": 4.0,
        "Atmos": 1.0,
        "Drinks": 2.0,
        "Value": 2.0,
        "Facilities": 2.0,
        "Total": 11.0
    },
    {
        "Pub": "The Gypsy Moth",
        "Area": "Greenwich",
        "latitude": 51.4822898183,
        "longitude": 0.0097826312,
        "Location": 4.0,
        "Atmos": null,
        "Drinks": null,
        "Value": null,
        "Facilities": 4.0,
        "Total": null
    },
    {
        "Pub": "The Gallery",
        "Area": "Pimlico",
        "latitude": 51.4887838188,
        "longitude": -0.1342950306,
        "Location": 3.0,
        "Atmos": 2.0,
        "Drinks": 4.0,
        "Value": null,
        "Facilities": 4.0,
        "Total": null
    },
    {
        "Pub": "Coach and Horses",
        "Area": "Brixton",
        "latitude": 51.45975214,
        "longitude": -0.1313889045,
        "Location": 2.0,
        "Atmos": 4.0,
        "Drinks": null,
        "Value": null,
        "Facilities": 3.0,
        "Total": null
    },
    {
        "Pub": "Marquis of Westminster",
        "Area": "Westminster",
        "latitude": 51.4918294,
        "longitude": -0.1408543,
        "Location": 2.0,
        "Atmos": 3.0,
        "Drinks": null,
        "Value": null,
        "Facilities": 3.0,
        "Total": null
    },
    {
        "Pub": "The Trafalgar Arms",
        "Area": "Tooting",
        "latitude": 51.4246916,
        "longitude": -0.1714295,
        "Location": 3.0,
        "Atmos": 3.0,
        "Drinks": 4.0,
        "Value": null,
        "Facilities": 3.0,
        "Total": null
    },
    {
        "Pub": "The Fox",
        "Area": "Custom House",
        "latitude": 51.5088231326,
        "longitude": 0.0254304307,
        "Location": 3.0,
        "Atmos": 3.0,
        "Drinks": null,
        "Value": null,
        "Facilities": 3.0,
        "Total": null
    },
    {
        "Pub": "White Horse & Bower",
        "Area": "Westminster",
        "latitude": 51.4949982,
        "longitude": -0.1308941,
        "Location": 3.0,
        "Atmos": 3.0,
        "Drinks": null,
        "Value": null,
        "Facilities": 3.0,
        "Total": null
    },
    {
        "Pub": "The Wellington",
        "Area": "Waterloo",
        "latitude": 51.5037667172,
        "longitude": -0.111386055,
        "Location": 4.0,
        "Atmos": 2.0,
        "Drinks": 4.0,
        "Value": null,
        "Facilities": 3.0,
        "Total": null
    },
    {
        "Pub": "The Park Tavern",
        "Area": "Finsbury Park",
        "latitude": 51.56811809,
        "longitude": -0.111223053,
        "Location": 2.0,
        "Atmos": 2.0,
        "Drinks": 4.0,
        "Value": null,
        "Facilities": 3.0,
        "Total": null
    },
    {
        "Pub": "The Scarsdale Tavern",
        "Area": "Kensington",
        "latitude": 51.496975,
        "longitude": -0.1990243,
        "Location": 3.0,
        "Atmos": 2.0,
        "Drinks": null,
        "Value": null,
        "Facilities": 3.0,
        "Total": null
    },
    {
        "Pub": "The Engineer",
        "Area": "Camden",
        "latitude": 51.5400622782,
        "longitude": -0.1507852413,
        "Location": 2.0,
        "Atmos": null,
        "Drinks": null,
        "Value": 2.0,
        "Facilities": 3.0,
        "Total": null
    },
    {
        "Pub": "Spice of Life",
        "Area": "Soho",
        "latitude": 51.51343182,
        "longitude": -0.1297843046,
        "Location": 4.0,
        "Atmos": null,
        "Drinks": null,
        "Value": null,
        "Facilities": 3.0,
        "Total": null
    },
    {
        "Pub": "One Tun",
        "Area": "Fitzrovia",
        "latitude": 51.519124,
        "longitude": -0.1367021,
        "Location": 3.0,
        "Atmos": 2.0,
        "Drinks": 4.0,
        "Value": null,
        "Facilities": 3.0,
        "Total": null
    },
    {
        "Pub": "White Hart",
        "Area": "Barnes",
        "latitude": 51.4710479361,
        "longitude": -0.2556664572,
        "Location": null,
        "Atmos": null,
        "Drinks": null,
        "Value": null,
        "Facilities": 3.0,
        "Total": null
    },
    {
        "Pub": "The Foxglove",
        "Area": "Angel",
        "latitude": 51.5392357,
        "longitude": -0.1068558611,
        "Location": 3.0,
        "Atmos": 3.0,
        "Drinks": null,
        "Value": null,
        "Facilities": 3.0,
        "Total": null
    },
    {
        "Pub": "Knowles of Norwood",
        "Area": "Norwood",
        "latitude": 51.4358687,
        "longitude": -0.1044546,
        "Location": 1.0,
        "Atmos": 3.0,
        "Drinks": null,
        "Value": null,
        "Facilities": 3.0,
        "Total": null
    },
    {
        "Pub": "Westminster Arms",
        "Area": "Westminster",
        "latitude": 51.50059565,
        "longitude": -0.1297889113,
        "Location": 3.0,
        "Atmos": 4.0,
        "Drinks": null,
        "Value": null,
        "Facilities": 2.0,
        "Total": null
    },
    {
        "Pub": "The Lemon Tree",
        "Area": "Covent Garden",
        "latitude": 51.5100165113,
        "longitude": -0.1256748994,
        "Location": 3.0,
        "Atmos": 3.0,
        "Drinks": null,
        "Value": null,
        "Facilities": 2.0,
        "Total": null
    },
    {
        "Pub": "The Greyhound",
        "Area": "Kensington",
        "latitude": 51.5010841447,
        "longitude": -0.1894406892,
        "Location": 3.0,
        "Atmos": 1.0,
        "Drinks": 2.0,
        "Value": null,
        "Facilities": 2.0,
        "Total": null
    },
    {
        "Pub": "The Builders Arms",
        "Area": "Kensington",
        "latitude": 51.4994438,
        "longitude": -0.188314,
        "Location": 3.0,
        "Atmos": 3.0,
        "Drinks": 2.0,
        "Value": null,
        "Facilities": 2.0,
        "Total": null
    },
    {
        "Pub": "Tamesis Dock",
        "Area": "Vauxhall",
        "latitude": 51.4919958,
        "longitude": -0.1221481,
        "Location": 5.0,
        "Atmos": 4.0,
        "Drinks": null,
        "Value": null,
        "Facilities": 2.0,
        "Total": null
    },
    {
        "Pub": "The White Lion",
        "Area": "Covent Garden",
        "latitude": 51.51280907,
        "longitude": -0.1238711896,
        "Location": 4.0,
        "Atmos": 4.0,
        "Drinks": null,
        "Value": null,
        "Facilities": 1.0,
        "Total": null
    },
    {
        "Pub": "The Cavendish Arms",
        "Area": "Stockwell",
        "latitude": 51.4765332,
        "longitude": -0.1276872,
        "Location": 2.0,
        "Atmos": 2.0,
        "Drinks": null,
        "Value": null,
        "Facilities": null,
        "Total": null
    },
    {
        "Pub": "The Phene",
        "Area": "Chelsea",
        "latitude": 51.485174,
        "longitude": -0.167575,
        "Location": 2.0,
        "Atmos": 2.0,
        "Drinks": null,
        "Value": null,
        "Facilities": null,
        "Total": null
    },
    {
        "Pub": "The Mayflower",
        "Area": "Rotherhithe",
        "latitude": 51.5017403798,
        "longitude": -0.0535638775,
        "Location": 4.0,
        "Atmos": null,
        "Drinks": null,
        "Value": null,
        "Facilities": null,
        "Total": null
    },
    {
        "Pub": "The Bill Murray",
        "Area": "Islington",
        "latitude": 51.536292,
        "longitude": -0.0988111,
        "Location": 2.0,
        "Atmos": null,
        "Drinks": null,
        "Value": null,
        "Facilities": null,
        "Total": null
    },
    {
        "Pub": "The Castle",
        "Area": "Angel",
        "latitude": 51.5319650233,
        "longitude": -0.1090171085,
        "Location": null,
        "Atmos": null,
        "Drinks": null,
        "Value": null,
        "Facilities": null,
        "Total": null
    },
    {
        "Pub": "The Spaniards Inn",
        "Area": "Hampstead",
        "latitude": 51.569884,
        "longitude": -0.1740278,
        "Location": 2.0,
        "Atmos": 4.0,
        "Drinks": 4.0,
        "Value": null,
        "Facilities": 5.0,
        "Total": null
    },
    {
        "Pub": "The Flask",
        "Area": "Hampstead",
        "latitude": 51.5565928063,
        "longitude": -0.1773346326,
        "Location": 4.0,
        "Atmos": 3.0,
        "Drinks": 2.0,
        "Value": null,
        "Facilities": 4.0,
        "Total": null
    }
]